mxnet/__init__.py
mxnet/_api_internal.py
mxnet/_global_var.py
mxnet/_numpy_op_doc.py
mxnet/api.py
mxnet/attribute.py
mxnet/autograd.py
mxnet/base.py
mxnet/callback.py
mxnet/context.py
mxnet/engine.py
mxnet/error.py
mxnet/executor.py
mxnet/executor_manager.py
mxnet/initializer.py
mxnet/libinfo.py
mxnet/libmxnet.dll
mxnet/libmxnet.lib
mxnet/libopenblas.dll
mxnet/library.py
mxnet/log.py
mxnet/lr_scheduler.py
mxnet/metric.py
mxnet/misc.py
mxnet/model.py
mxnet/monitor.py
mxnet/name.py
mxnet/ndarray_doc.py
mxnet/numpy_dispatch_protocol.py
mxnet/numpy_op_fallback.py
mxnet/numpy_op_signature.py
mxnet/operator.py
mxnet/profiler.py
mxnet/random.py
mxnet/recordio.py
mxnet/registry.py
mxnet/rtc.py
mxnet/runtime.py
mxnet/space.py
mxnet/symbol_doc.py
mxnet/test_utils.py
mxnet/torch.py
mxnet/tvmop.py
mxnet/util.py
mxnet/visualization.py
mxnet/_ctypes/__init__.py
mxnet/_ctypes/ndarray.py
mxnet/_ctypes/space.py
mxnet/_ctypes/symbol.py
mxnet/_cy3/__init__.py
mxnet/_ffi/__init__.py
mxnet/_ffi/base.py
mxnet/_ffi/function.py
mxnet/_ffi/node_generic.py
mxnet/_ffi/object.py
mxnet/_ffi/runtime_ctypes.py
mxnet/_ffi/_ctypes/__init__.py
mxnet/_ffi/_ctypes/function.py
mxnet/_ffi/_ctypes/object.py
mxnet/_ffi/_ctypes/types.py
mxnet/_ffi/_cy3/__init__.py
mxnet/contrib/__init__.py
mxnet/contrib/autograd.py
mxnet/contrib/io.py
mxnet/contrib/ndarray.py
mxnet/contrib/quantization.py
mxnet/contrib/symbol.py
mxnet/contrib/tensorboard.py
mxnet/contrib/amp/__init__.py
mxnet/contrib/amp/amp.py
mxnet/contrib/amp/loss_scaler.py
mxnet/contrib/amp/lists/__init__.py
mxnet/contrib/amp/lists/symbol_bf16.py
mxnet/contrib/amp/lists/symbol_fp16.py
mxnet/contrib/onnx/__init__.py
mxnet/contrib/onnx/onnx2mx/__init__.py
mxnet/contrib/onnx/onnx2mx/_import_helper.py
mxnet/contrib/onnx/onnx2mx/_op_translations.py
mxnet/contrib/onnx/onnx2mx/_translation_utils.py
mxnet/contrib/onnx/onnx2mx/import_model.py
mxnet/contrib/onnx/onnx2mx/import_onnx.py
mxnet/contrib/onnx/onnx2mx/import_to_gluon.py
mxnet_alas-0.0.5.dist-info/METADATA
mxnet_alas-0.0.5.dist-info/WHEEL
mxnet_alas-0.0.5.dist-info/top_level.txt
mxnet_alas-0.0.5.dist-info/RECORD
